{"openapi":"3.0.0","paths":{"/":{"get":{"operationId":"AppController_getHello","parameters":[],"responses":{"200":{"description":"","content":{"application/json":{"schema":{"type":"string"}}}}},"tags":["App"]}},"/troceria":{"post":{"operationId":"TroceriaController_create","parameters":[],"requestBody":{"required":true,"content":{"application/json":{"schema":{"$ref":"#/components/schemas/CreateEntradaDto"}}}},"responses":{"201":{"description":"","content":{"application/json":{"schema":{"type":"object"}}}}},"security":[{"bearer":[]}],"tags":["Trocer├¡a (Materia Prima)"]},"get":{"operationId":"TroceriaController_findAll","parameters":[],"responses":{"200":{"description":"","content":{"application/json":{"schema":{"type":"array","items":{"type":"object"}}}}}},"security":[{"bearer":[]}],"tags":["Trocer├¡a (Materia Prima)"]}},"/troceria/{id}":{"get":{"operationId":"TroceriaController_findOne","parameters":[{"name":"id","required":true,"in":"path","schema":{"type":"number"}}],"responses":{"200":{"description":"","content":{"application/json":{"schema":{"type":"object"}}}}},"security":[{"bearer":[]}],"tags":["Trocer├¡a (Materia Prima)"]},"delete":{"operationId":"TroceriaController_removeEntrada","parameters":[{"name":"id","required":true,"in":"path","schema":{"type":"number"}}],"responses":{"200":{"description":""}},"security":[{"bearer":[]}],"tags":["Trocer├¡a (Materia Prima)"]}},"/troceria/{id}/summary":{"get":{"operationId":"TroceriaController_getSummary","parameters":[{"name":"id","required":true,"in":"path","schema":{"type":"number"}}],"responses":{"200":{"description":""}},"security":[{"bearer":[]}],"tags":["Trocer├¡a (Materia Prima)"]}},"/troceria/{id}/trozas":{"post":{"operationId":"TroceriaController_addTroza","parameters":[{"name":"id","required":true,"in":"path","schema":{"type":"number"}}],"requestBody":{"required":true,"content":{"application/json":{"schema":{"$ref":"#/components/schemas/AddTrozaDto"}}}},"responses":{"201":{"description":"","content":{"application/json":{"schema":{"type":"object"}}}}},"security":[{"bearer":[]}],"tags":["Trocer├¡a (Materia Prima)"]}},"/troceria/{id}/trozas/{trozaId}":{"delete":{"operationId":"TroceriaController_removeTroza","parameters":[{"name":"id","required":true,"in":"path","schema":{"type":"number"}},{"name":"trozaId","required":true,"in":"path","schema":{"type":"number"}}],"responses":{"200":{"description":"","content":{"application/json":{"schema":{"type":"object"}}}}},"security":[{"bearer":[]}],"tags":["Trocer├¡a (Materia Prima)"]},"patch":{"operationId":"TroceriaController_updateTroza","parameters":[{"name":"id","required":true,"in":"path","schema":{"type":"number"}},{"name":"trozaId","required":true,"in":"path","schema":{"type":"number"}}],"responses":{"200":{"description":"","content":{"application/json":{"schema":{"type":"object"}}}}},"security":[{"bearer":[]}],"tags":["Trocer├¡a (Materia Prima)"]}},"/troceria/{id}/finalizar":{"patch":{"operationId":"TroceriaController_finalizar","parameters":[{"name":"id","required":true,"in":"path","schema":{"type":"number"}}],"responses":{"200":{"description":"","content":{"application/json":{"schema":{"type":"object"}}}}},"security":[{"bearer":[]}],"tags":["Trocer├¡a (Materia Prima)"]}},"/produccion":{"post":{"operationId":"ProduccionController_create","parameters":[],"requestBody":{"required":true,"content":{"application/json":{"schema":{"$ref":"#/components/schemas/CreateEntradaDto"}}}},"responses":{"201":{"description":"","content":{"application/json":{"schema":{"type":"object"}}}}},"security":[{"bearer":[]}],"tags":["Producci├│n (Corte y Medici├│n)"]},"get":{"operationId":"ProduccionController_findAll","parameters":[],"responses":{"200":{"description":"","content":{"application/json":{"schema":{"type":"array","items":{"type":"object"}}}}}},"security":[{"bearer":[]}],"tags":["Producci├│n (Corte y Medici├│n)"]}},"/produccion/{id}":{"get":{"operationId":"ProduccionController_findOne","parameters":[{"name":"id","required":true,"in":"path","schema":{"type":"number"}}],"responses":{"200":{"description":"","content":{"application/json":{"schema":{"type":"object"}}}}},"security":[{"bearer":[]}],"tags":["Producci├│n (Corte y Medici├│n)"]},"delete":{"operationId":"ProduccionController_removeEntrada","parameters":[{"name":"id","required":true,"in":"path","schema":{"type":"number"}}],"responses":{"200":{"description":""}},"security":[{"bearer":[]}],"tags":["Producci├│n (Corte y Medici├│n)"]}},"/produccion/{id}/summary":{"get":{"operationId":"ProduccionController_getSummary","parameters":[{"name":"id","required":true,"in":"path","schema":{"type":"number"}}],"responses":{"200":{"description":""}},"security":[{"bearer":[]}],"tags":["Producci├│n (Corte y Medici├│n)"]}},"/produccion/{id}/piezas":{"post":{"operationId":"ProduccionController_addPieza","parameters":[{"name":"id","required":true,"in":"path","schema":{"type":"number"}}],"requestBody":{"required":true,"content":{"application/json":{"schema":{"$ref":"#/components/schemas/AddPiezaDto"}}}},"responses":{"201":{"description":"","content":{"application/json":{"schema":{"type":"object"}}}}},"security":[{"bearer":[]}],"tags":["Producci├│n (Corte y Medici├│n)"]}},"/produccion/{id}/piezas/{piezaId}":{"delete":{"operationId":"ProduccionController_removePieza","parameters":[{"name":"id","required":true,"in":"path","schema":{"type":"number"}},{"name":"piezaId","required":true,"in":"path","schema":{"type":"number"}}],"responses":{"200":{"description":"","content":{"application/json":{"schema":{"type":"object"}}}}},"security":[{"bearer":[]}],"tags":["Producci├│n (Corte y Medici├│n)"]},"patch":{"operationId":"ProduccionController_updatePieza","parameters":[{"name":"id","required":true,"in":"path","schema":{"type":"number"}},{"name":"piezaId","required":true,"in":"path","schema":{"type":"number"}}],"responses":{"200":{"description":"","content":{"application/json":{"schema":{"type":"object"}}}}},"security":[{"bearer":[]}],"tags":["Producci├│n (Corte y Medici├│n)"]}},"/produccion/{id}/finalizar":{"patch":{"operationId":"ProduccionController_finalizar","parameters":[{"name":"id","required":true,"in":"path","schema":{"type":"number"}}],"responses":{"200":{"description":"","content":{"application/json":{"schema":{"type":"object"}}}}},"security":[{"bearer":[]}],"tags":["Producci├│n (Corte y Medici├│n)"]}},"/users":{"post":{"operationId":"UsersController_create","parameters":[],"requestBody":{"required":true,"content":{"application/json":{"schema":{"$ref":"#/components/schemas/CreateUserDto"}}}},"responses":{"201":{"description":""}},"security":[{"bearer":[]}],"tags":["Usuarios"]},"get":{"operationId":"UsersController_findAll","parameters":[],"responses":{"200":{"description":""}},"security":[{"bearer":[]}],"tags":["Usuarios"]}},"/users/{id}":{"get":{"operationId":"UsersController_findOne","parameters":[{"name":"id","required":true,"in":"path","schema":{"type":"number"}}],"responses":{"200":{"description":""}},"security":[{"bearer":[]}],"tags":["Usuarios"]},"patch":{"operationId":"UsersController_update","parameters":[{"name":"id","required":true,"in":"path","schema":{"type":"number"}}],"requestBody":{"required":true,"content":{"application/json":{"schema":{"$ref":"#/components/schemas/UpdateUserDto"}}}},"responses":{"200":{"description":""}},"security":[{"bearer":[]}],"tags":["Usuarios"]},"delete":{"operationId":"UsersController_remove","parameters":[{"name":"id","required":true,"in":"path","schema":{"type":"number"}}],"responses":{"200":{"description":""}},"security":[{"bearer":[]}],"tags":["Usuarios"]}},"/auth/login":{"post":{"operationId":"AuthController_login","parameters":[],"requestBody":{"required":true,"content":{"application/json":{"schema":{"$ref":"#/components/schemas/LoginDto"}}}},"responses":{"200":{"description":""}},"tags":["Autenticaci├│n"]}},"/dashboard/metrics":{"get":{"operationId":"DashboardController_getMetrics","parameters":[],"responses":{"200":{"description":""}},"security":[{"bearer":[]}],"tags":["Dashboard"]}},"/dashboard/chart":{"get":{"operationId":"DashboardController_getDailyChart","parameters":[],"responses":{"200":{"description":""}},"security":[{"bearer":[]}],"tags":["Dashboard"]}},"/dashboard/recent-entries":{"get":{"operationId":"DashboardController_getRecentEntries","parameters":[],"responses":{"200":{"description":""}},"security":[{"bearer":[]}],"tags":["Dashboard"]}}},"info":{"title":"Cubi API","description":"The API documentation for the Cubi sawmill operation management system.","version":"1.0","contact":{}},"tags":[],"servers":[{"url":"https://cubi-api.onrender.com/","description":"Servidor de Producci├│n"},{"url":"http://localhost:3000","description":"Entorno Local"}],"components":{"securitySchemes":{"bearer":{"scheme":"bearer","bearerFormat":"JWT","type":"http"}},"schemas":{"CreateEntradaDto":{"type":"object","properties":{"fecha":{"type":"string"},"turno":{"type":"string","enum":["Matutino","Vespertino","Nocturno"]}},"required":["fecha","turno"]},"AddTrozaDto":{"type":"object","properties":{"diametro1":{"type":"number","minimum":1},"diametro2":{"type":"number","minimum":1},"largo":{"type":"number","minimum":1},"descuento":{"type":"number","minimum":0,"maximum":100}},"required":["diametro1","diametro2","largo","descuento"]},"AddPiezaDto":{"type":"object","properties":{"grueso":{"type":"number","minimum":1},"clase":{"type":"number"},"ancho":{"type":"number","minimum":1},"largo":{"type":"number","minimum":1},"verde":{"type":"number","minimum":0},"estufa":{"type":"number","minimum":0}},"required":["grueso","clase","ancho","largo","verde","estufa"]},"CreateUserDto":{"type":"object","properties":{"username":{"type":"string","minLength":3},"password":{"type":"string","minLength":6},"nombres":{"type":"string"},"apellidos":{"type":"string"},"role":{"type":"object"}},"required":["username","password","nombres","apellidos","role"]},"UpdateUserDto":{"type":"object","properties":{}},"LoginDto":{"type":"object","properties":{"username":{"type":"string"},"password":{"type":"string","minLength":6}},"required":["username","password"]}}}}
